{"ocr_results":[{"text":"124","box":[[91,49],[171,49],[171,70],[91,70]]},{"text":"风暴历程一文革中的人民解放军","box":[[179,48],[468,48],[468,65],[179,65]]},{"text":"常委决定由周、邓、彭三人来处理罗的问题，以后又指定三人小组管这个","box":[[209,121],[816,121],[816,141],[209,141]]},{"text":"会议。这个会搞了一个多月，党对他很耐心，负责，帮助。大家摆事实、讲","box":[[166,155],[818,156],[818,176],[166,175]]},{"text":"道理。对罗的问题，过去我不知道，到上海还不知道，只知道他作风不好，","box":[[167,191],[801,192],[801,212],[167,211]]},{"text":"但思想还开放。现在揭发出来，特别他这一跳，就更没有话说了。","box":[[168,227],[713,227],[713,247],[168,247]]},{"text":"我同意工作小组的报告。我认为，解决罗的问题，是党的一个重大胜","box":[[206,261],[816,262],[816,282],[206,281]]},{"text":"利。我们没有察觉，林总首先察觉，很负责地向中央、主席提出，嗅觉比我们","box":[[166,297],[815,298],[815,318],[166,317]]},{"text":"灵敏得多。主席亲自关怀、指导这个斗争。罗的问题性质是严重的，比上海估","box":[[170,335],[815,335],[815,353],[170,353]]},{"text":"计的还严重得多。我们还是帮，希望他改正错误。开始是背靠背、“调离”军","box":[[166,369],[817,370],[817,390],[166,389]]},{"text":"队，他抵触情绪很大，只有面对面。来了个自杀，自已作了结论，无非是抵抗","box":[[169,407],[816,407],[816,424],[169,424]]},{"text":"到死。","box":[[168,441],[213,441],[213,460],[168,460]]},{"text":"如果你是正确的，应当坚持。主席受过机会主义多次打击，开除党籍，","box":[[207,476],[802,477],[802,497],[207,496]]},{"text":"就是坚持，不怕孤立，正确的总要胜利。不同意见可以保留。彭德怀作了结","box":[[167,511],[816,512],[816,532],[167,531]]},{"text":"论，几万言翻案，还分配工作，主席对他说，你保留你的，我保留我的。是","box":[[167,548],[816,549],[816,567],[167,566]]},{"text":"不是还有不可告人的事，最少说明抗拒到底。","box":[[169,585],[537,585],[537,602],[169,602]]},{"text":"罗担负的职务很多、很大。书记处书记，副总理，总参谋长，秘书长等","box":[[206,618],[816,619],[816,639],[206,638]]},{"text":"等，掌握军事大权。军队是党的命脉，无产阶级专政的命脉，让这样没有党","box":[[166,653],[817,654],[817,674],[166,673]]},{"text":"性、作风这样恶劣、资产阶级思想充满脑袋的人掌握军队是极危险的。退一","box":[[167,688],[818,690],[818,710],[167,708]]},{"text":"步说，即使没有个人野心，向党伸手，凭他那种思想作风也是危险的。他确实","box":[[168,725],[815,726],[815,744],[168,743]]},{"text":"是个隐患，拔除这个隐患就是个大胜利。何况他又有伸手问题。一旦天下有","box":[[167,761],[814,762],[814,780],[167,779]]},{"text":"事，那就不堪设想。","box":[[166,795],[328,797],[327,817],[166,815]]},{"text":"罗瑞卿的错误性质，同意报告中指出的，是在社会主义革命斗争中资产阶","box":[[207,831],[815,832],[815,852],[207,851]]},{"text":"级思想在党内军内的反映。他对毛主席思想是反对的，当公安部长时就搞阶","box":[[169,869],[814,869],[814,886],[169,886]]},{"text":"级斗争熄灭论，十无运动。到军队后又同林总唱对台戏，一个稿子修改七八","box":[[167,903],[816,904],[816,922],[167,921]]},{"text":"次，真不可理解，就是要宣传他的资产阶级思想。他还到处讲话，煽动，","box":[[167,937],[802,939],[802,959],[167,957]]},{"text":"反对毛主席的建军思想，反对林总的正确领导。罗是资产阶级极端个人主义","box":[[167,972],[816,973],[816,993],[167,992]]},{"text":"者，不是普通的，而是极端的。过去只知道他锋芒毕露。他私心很重，我字","box":[[168,1011],[815,1011],[815,1028],[168,1028]]},{"text":"第一，个人打算很多，不能得罪他，得罪他一句，成百倍地回敬你。他记性又","box":[[166,1043],[816,1044],[816,1064],[166,1063]]},{"text":"好，伸了一下舌头也记几年，极端个人主义已发展到狂妄的程度。他不守纪律","box":[[167,1081],[816,1081],[816,1098],[167,1098]]},{"text":"是一贯的，走后门，不走正门，走邪道，不走正道，不搞党的正常生活，而且","box":[[166,1114],[816,1115],[816,1135],[166,1134]]},{"text":"背后搞鬼。在我们党内，一切问题都可以经过党的原则来解决。我们也经常","box":[[167,1149],[816,1150],[816,1170],[167,1169]]},{"text":"犯错误，主席著作学得不好，有时有主观主义，片面性，通过党的生活改正","box":[[167,1184],[816,1185],[816,1205],[167,1204]]},{"text":"就行了。罗的错误也没有什么，改正就行了。十年改正就行了。但是他是不会","box":[[168,1219],[815,1220],[815,1240],[168,1239]]}],"dimensions":{"height":1346,"width":938}}