{"ocr_results":[{"text":"第四章1967·上：淫雨霏霏","box":[[510,57],[743,57],[743,74],[510,74]]},{"text":"331","box":[[817,57],[850,57],[850,77],[817,77]]},{"text":"看军区司令部1966年的大字报，梁兴初不同意，就被他们戴上高帽批斗，并推","box":[[78,127],[819,128],[819,149],[78,148]]},{"text":"倒在地。是日及28日，军区文艺团体和军区院校的造反派还以查阅军区文化大革","box":[[78,162],[818,164],[818,184],[78,182]]},{"text":"命的有关文件和“黑材料”为由，相继抄了军区文革小组前任和现任负责人相炜、","box":[[79,198],[803,200],[803,220],[79,218]]},{"text":"文年生的家，抄走了相炜保存在家的有关文革的机密文件。[636]","box":[[73,230],[650,223],[651,257],[73,264]]},{"text":"1月28日晚，军体院毛泽东思想战斗团、部队文艺工作者红色联合造反团南","box":[[119,270],[817,271],[817,291],[119,290]]},{"text":"下造反团、军区战士歌舞团千钧棒战斗队等组织，抄了部分军区领导的家，并把","box":[[79,305],[818,307],[818,326],[79,324]]},{"text":"萧元礼副政委带走了。1月31日，军区造反派又冲击军区政治部。当晚，他们要","box":[[77,340],[818,342],[818,362],[77,360]]},{"text":"在军区礼堂召开斗争胜利大会，并要军区副参谋长以上干部和警卫部队连以上干","box":[[77,375],[817,377],[817,397],[77,395]]},{"text":"部参加。当时谣传陈伯达对桂林步校的人说，广州军区应撤销一切警卫部队，给","box":[[77,412],[818,413],[818,433],[77,432]]},{"text":"革命师生一切方便，使造反派兴奋不已，中大八三一发表了一份支持军区造反派","box":[[78,447],[816,449],[816,469],[78,467]]},{"text":"的声明。","box":[[78,484],[146,484],[146,502],[78,502]]},{"text":"2月5日下午，广州军区部分文体工作者和军体院学员，联合了中大红旗、珠","box":[[120,520],[818,521],[818,539],[120,538]]},{"text":"影东方红等二十几个群众组织共四五百人，冲击军区第二门诊部，直到次日清晨","box":[[76,554],[816,556],[816,576],[76,574]]},{"text":"才陆续离去。2月7日，军区卫生学校革命造反联络站等单位，包围冲击了军区后","box":[[76,589],[816,591],[816,611],[76,609]]},{"text":"勤部和陆军医院。","box":[[78,627],[229,627],[229,644],[78,644]]},{"text":"2月8日凌晨，军内的造反组织在军区礼堂抓人打斗，气氛相当暴烈。事情","box":[[119,660],[815,662],[815,683],[119,681]]},{"text":"的起因，是战士杂技团在一次开会，大家喊“毛主席方岁”时，有一名演员不喊","box":[[78,697],[799,699],[799,717],[78,715]]},{"text":"并说“不搞形式主义”。凌晨3时，军区派出部队，拘留了二十多名闹事人员。军","box":[[76,732],[818,734],[818,754],[76,752]]},{"text":"区部分文体工作者和军体院学员两千多人，在军区门外举行静坐示威，并得到北","box":[[76,768],[816,769],[816,789],[76,788]]},{"text":"航红旗、“哈军工”、中大红旗、珠影东方红等组织的支持。","box":[[78,806],[604,806],[604,823],[78,823]]},{"text":"2月8日白天，军区司令部、政治部和警卫营的大门外，聚集了大批群众，","box":[[118,839],[801,840],[801,860],[118,859]]},{"text":"他们来自省革联属下30多个组织。据说，是接到七中红旗的通知，说军区把千","box":[[77,874],[816,876],[816,896],[77,894]]},{"text":"钧棒的人抓走了，于是赶来声援千钧棒的。","box":[[77,909],[456,910],[456,930],[77,929]]},{"text":"当日，广州军区发表了措辞严厉的公告称：","box":[[124,948],[503,948],[503,965],[124,965]]},{"text":"有极少数别有用心的人，竟敢公然违抗毛主席的指示和中央军委命令，","box":[[162,992],[756,993],[756,1013],[162,1012]]},{"text":"知法犯法。他们煽动一些不明真相的群众，甚至假借中央负责同志名义，造谣","box":[[122,1028],[769,1029],[769,1047],[122,1046]]},{"text":"惑众，冲击军事领导机关，企图把斗争锋芒引向军队；他们随便搜家抓人，","box":[[121,1062],[757,1063],[757,1083],[121,1082]]},{"text":"侮辱人格，实行体罚，甚至捆绑罚跪，毒打群众；他们到一些担负战备任务，","box":[[120,1098],[755,1100],[755,1117],[120,1115]]},{"text":"按照中央军委指示暂不开展“四大”（大鸣、大放、大字报、大辩论）或实行","box":[[121,1133],[769,1134],[769,1152],[121,1151]]},{"text":"正面教育的单位去煽风点火，强行逼迫那里的群众和领导立即开展“四大”；","box":[[122,1168],[766,1169],[766,1187],[122,1186]]},{"text":"【636】《中国人民解放军广州军区史》中册，页636-637。","box":[[74,1243],[525,1246],[525,1263],[74,1260]]}],"dimensions":{"height":1349,"width":939}}