{"ocr_results":[{"text":"480","box":[[94,48],[178,48],[178,66],[94,66]]},{"text":"风暴历程一文革中的人民解放军","box":[[182,45],[471,45],[471,62],[182,62]]},{"text":"林彪副主席最全面、最正确、最科学地评价了伟大领袖毛主席和伟大的","box":[[210,116],[818,118],[818,138],[210,136]]},{"text":"毛泽东思想。他指出：毛主席是当代的列宁。像毛主席这样的天才，中国几千","box":[[171,152],[818,154],[818,175],[171,172]]},{"text":"年，世界几百年才出现一个。毛主席是当代无产阶级最杰出的领袖，是当代最","box":[[170,189],[819,191],[819,211],[170,209]]},{"text":"伟大的天才，是我们时代的代表。毛主席比马克思、恩格斯、列宁、斯大林","box":[[170,224],[819,226],[819,246],[170,244]]},{"text":"高得多。所有前辈的马克思列宁主义者，谁也没有像毛主席那祥亲自指挥过那","box":[[172,260],[818,262],[818,282],[172,280]]},{"text":"么多重大的政治战役和军事战役；谁也没有像毛主席经历过那样长期、那样","box":[[172,297],[817,299],[817,316],[172,314]]},{"text":"复杂、那样多方面的斗争；谁也没有像毛主席那样解决了那么多无产阶级革命","box":[[169,331],[818,332],[818,352],[169,351]]},{"text":"和无产阶级专政一系列重大的理论和实践问题。他指出：毛泽东思想是我们时","box":[[170,367],[817,369],[817,387],[170,385]]},{"text":"代的旗帜，是人类的灯塔，是世界革命的最锐利的武器，是放之四海而皆准","box":[[170,402],[817,403],[817,423],[170,422]]},{"text":"的普遍真理，是当代最高水平的马克思列宁主义。毛泽东思想是全党全军和","box":[[170,437],[819,439],[819,459],[170,457]]},{"text":"全国人民的统一的行动纲领。林彪副主席对毛主席、对毛泽东思想所作出的","box":[[168,473],[818,474],[818,494],[168,493]]},{"text":"最全面、最正确、最科学的评价，字字句句表达了亿万革命人民的愿望，宇字","box":[[170,508],[818,511],[818,531],[170,529]]},{"text":"句句说到了亿万人民的心坎里，极大地增强了全国和全世界革命人民对伟大领","box":[[170,544],[819,546],[819,567],[170,565]]},{"text":"袖毛主席的无限热爱的感情，极大地提高了全国和全世界革命人民学习和掌握","box":[[170,580],[817,582],[817,602],[170,600]]},{"text":"毛泽东思想的革命自觉性。","box":[[172,618],[381,618],[381,635],[172,635]]},{"text":"·...","box":[[213,655],[243,655],[243,671],[213,671]]},{"text":"林彪副主席最英明、最积极、最认真地领导和组织了毛泽东思想的大普及","box":[[209,687],[818,688],[818,708],[209,707]]},{"text":"运动，开创了工农兵直接掌握马克思列宁主义、毛泽东思想的新纪元。·.","box":[[169,722],[817,724],[817,744],[169,742]]},{"text":"他发出了“人人读毛主席的书，听毛主席的话，照毛主席的指示办事，做毛主","box":[[169,758],[818,759],[818,779],[169,778]]},{"text":"席的好战士”的伟大号召。他提出：学习毛主席著作，要带着问题学，活学活","box":[[170,793],[818,795],[818,815],[170,813]]},{"text":"用，学用结合，急用先学，立竿见影，在“用”字上狠下功夫。这是行之有效","box":[[169,828],[819,830],[819,851],[169,848]]},{"text":"的、普遍适用的、理论联系实际的马克思列宁主义的原则和方法。随着学习","box":[[169,865],[818,867],[818,887],[169,885]]},{"text":"运动的发展，他不断提出新的要求，不断总结新的经验，不断树立新的先进","box":[[169,900],[819,902],[819,922],[169,920]]},{"text":"典型。他把无产阶级文化大革命的根本任务，高度概括为一句话，“就是要大","box":[[169,936],[818,938],[818,958],[169,956]]},{"text":"立毛泽东思想”。他把波澜壮阔的活学活用毛主席著作群众运动从全军推向全","box":[[171,972],[817,974],[817,992],[171,990]]},{"text":"国，现在正由全国逐步推向全世界。这种大好局面，是马克思列宁主义发展","box":[[170,1006],[819,1008],[819,1028],[170,1026]]},{"text":"史上空前未有的。这是林彪副主席对中国革命和世界革命最卓越、最杰出、","box":[[171,1041],[805,1043],[805,1063],[171,1061]]},{"text":"最伟大的贡献。他的这个伟大贡献，深受中国人民和全世界人民最热烈最衷","box":[[170,1077],[817,1079],[817,1097],[170,1095]]},{"text":"心的感激，值得我们子孙万代大颂特颂、大书特书。他的这个伟大贡献，将","box":[[170,1112],[818,1115],[818,1132],[170,1129]]},{"text":"作为划时代的伟大创举，载入国际共产主义运动的光辉史册。[933]","box":[[164,1145],[714,1137],[714,1171],[165,1179]]},{"text":"【933】《海军首次学习毛主席著作积极分子代表大会主要材料》，页82-88。","box":[[119,1232],[709,1236],[709,1256],[119,1252]]}],"dimensions":{"height":1348,"width":937}}