{"ocr_results":[{"text":"第六章1967·下：浊浪排空","box":[[494,47],[726,47],[726,64],[494,64]]},{"text":"501","box":[[802,45],[835,45],[835,67],[802,67]]},{"text":"15.民族事务委员会","box":[[109,119],[279,119],[279,139],[109,139]]},{"text":"9月，驻中共中央统战部军事代表向民族事务委员会系统派驻九人组成的军","box":[[107,154],[801,155],[801,176],[107,175]]},{"text":"代表小组，组长陈长勇，副组长刘玉田。1970年，驻中共中央统战部军事代表派","box":[[61,190],[802,191],[802,211],[61,210]]},{"text":"出第二任军管小组，组长唐铁依，副组长张玉超。","box":[[63,227],[507,227],[507,247],[63,247]]},{"text":"16.科学技术委员会","box":[[109,263],[279,263],[279,280],[109,280]]},{"text":"1967年1月17日，科学技术委员会曾被夺权并成立革命造反司令部。1967","box":[[108,298],[800,299],[800,317],[108,316]]},{"text":"年3月，改称革命委员会，张本（原科委政策研究室主任）任主任。1968年3","box":[[60,332],[804,334],[804,354],[60,352]]},{"text":"月19日，张本被北京卫戌区逮捕。9月19日，中央决定对科学技术委员会实行","box":[[63,370],[800,370],[800,387],[63,387]]},{"text":"军事管制。军管人员由高等军事学院派遣。任命石煌为军管会主任，崔星为副主","box":[[62,404],[802,404],[802,424],[62,424]]},{"text":"任。【989】","box":[[59,439],[129,429],[132,450],[62,460]]},{"text":"综上所述，1967-68年，国务院共有部（委）机构共48个，除国防部为虚设，","box":[[107,474],[788,475],[788,495],[107,494]]},{"text":"公安部、文化部未实行军管外，实行军管的部（委）共45个，占96%（不计国防","box":[[61,511],[801,512],[801,532],[61,531]]},{"text":"部)。本节所列部（委）共39个（第二至第七机械工业部另述），其中组成军管会","box":[[61,546],[801,547],[801,567],[61,566]]},{"text":"的18个，组成军管小组的三个，派出军事代表的18个。39个部（委）中，由总","box":[[60,581],[801,583],[801,603],[60,601]]},{"text":"参谋部机关负责派遣人员的七个，总后勤部五个，海军四个，空军三个，炮兵两","box":[[61,617],[801,618],[801,638],[61,637]]},{"text":"个，装甲兵一个，工程兵五个，铁道兵一个，通信兵部两个，防化学兵部一个，","box":[[60,652],[788,653],[788,673],[60,672]]},{"text":"高等军事学院一个，先军事科学院后为工程兵一个，北京军区两个，南京军区一","box":[[62,688],[801,689],[801,709],[62,708]]},{"text":"个，多部门或其他三个。","box":[[61,724],[275,724],[275,744],[61,744]]},{"text":"以上所列担任国务院各部（委）军管机构领导或军事代表的军方派出负责人","box":[[107,759],[800,760],[800,780],[107,779]]},{"text":"员共113人，最高职务者为各军兵种或大军区副职，最低为团级。多个部（委）","box":[[61,795],[801,796],[801,816],[61,815]]},{"text":"第一把手仅为师级干部。其中取消军衔前中将3人，少将20人，大校28人，占","box":[[60,830],[801,831],[801,852],[60,851]]},{"text":"113人中的45%。即军方派出负责人员中大校以上高级干部比例不到50%。与派驻","box":[[62,869],[800,869],[800,886],[62,886]]},{"text":"省级军管负责人级别不可同日而言。","box":[[63,904],[376,904],[376,921],[63,921]]},{"text":"三、对国务院直属机构及秘书厅的军事管制","box":[[226,949],[638,949],[638,969],[226,969]]},{"text":"1967-68年，国务院直属机构名义上共为22个。其中中国农业银行与中国人","box":[[109,995],[800,995],[800,1012],[109,1012]]},{"text":"民银行为一套机构，两块牌子，实为21个。除中国民用航空总局1967年1月已","box":[[63,1030],[800,1030],[800,1047],[63,1047]]},{"text":"由空军接管，国家海洋局由海军代管列入军队序列，国家档案局、国务院科学技","box":[[64,1064],[799,1064],[799,1081],[64,1081]]},{"text":"术于部局情况未详外，其余17个单位及国务院秘书厅先后实行军事管制。","box":[[62,1099],[721,1099],[721,1116],[62,1116]]},{"text":"【989】石煌，时任高等军事学院战役教研室副主任。崔星，时任高等军事学院战役教研室教","box":[[60,1212],[801,1212],[801,1229],[60,1229]]},{"text":"员，1965年大校军衔。","box":[[128,1235],[297,1235],[297,1252],[128,1252]]}],"dimensions":{"height":1348,"width":935}}