{"ocr_results":[{"text":"第一章1965：风起苹末","box":[[545,48],[742,48],[742,65],[545,65]]},{"text":"49","box":[[826,46],[851,46],[851,68],[826,68]]},{"text":"中人民政","box":[[719,122],[758,122],[758,326],[719,326]]},{"text":"国","box":[[737,154],[749,154],[749,176],[737,176]]},{"text":"人民邮","box":[[730,191],[751,191],[751,264],[730,264]]},{"text":"林彪的形象首次出","box":[[208,306],[356,306],[356,326],[208,326]]},{"text":"现在新中国的邮票上，","box":[[183,331],[354,331],[354,352],[183,352]]},{"text":"8","box":[[724,322],[752,322],[752,366],[724,366]]},{"text":"1965年1月31日。","box":[[182,355],[350,358],[350,378],[182,375]]},{"text":"一套共3枚的纪念邮票。图案分别是毛泽东像和《雄关漫道真如铁，而今迈步从","box":[[76,437],[816,438],[816,458],[76,457]]},{"text":"头越》、《决战前夕》两幅油画。其中《雄关漫道真如铁，而今迈步从头越》为总","box":[[78,475],[814,475],[814,492],[78,492]]},{"text":"政下属的中国人民革命军事博物馆彭彬，根据毛泽东的词《忆秦娥（娄山关）》创","box":[[75,508],[817,509],[817,529],[75,528]]},{"text":"作。画面中虚构了毛泽东与林彪长征途中在遵义娄山关上的形象。同时间出版的","box":[[75,543],[816,544],[816,564],[75,563]]},{"text":"《人民画报》1965年第一期，亦以两版的显著篇幅，刊登了这幅油画。","box":[[74,578],[699,579],[699,599],[74,598]]},{"text":"这一幅油画，将毛、林在一起“并肩战斗”的艺术形象首次公开呈现在全国","box":[[118,614],[816,615],[816,635],[118,634]]},{"text":"公众面前。它在毛对刘少奇不满的时候出现，准确地预示了一年多以后“刘下林","box":[[76,651],[815,652],[815,670],[76,669]]},{"text":"上”的政治变局。","box":[[74,685],[231,685],[231,705],[74,705]]},{"text":"1965年1月，三届全国人大一次会议再次任命林彪为国务院副总理兼国防部","box":[[120,722],[815,723],[815,741],[120,740]]},{"text":"部长。与6年前的二届全国人大一次会议不同，林彪取代陈云在副总理中排名第","box":[[76,756],[816,757],[816,777],[76,776]]},{"text":"一。陈云退居为次，邓小平则名列第三。","box":[[77,794],[436,794],[436,811],[77,811]]},{"text":"其实，林彪的擢升并非偶然，建国后毛泽东一直在政治上倚重他。尽管林彪","box":[[121,828],[816,828],[816,848],[121,848]]},{"text":"以怕光、怕风、怕水为由长期养病，但他在党内地位仍不断上升。1955年4月在","box":[[76,862],[816,863],[816,883],[76,882]]},{"text":"中共七届五中全会上，他被补选为中央政治局委员；1958年5月，更是第一次超","box":[[76,898],[816,899],[816,919],[76,918]]},{"text":"越彭德怀，在八大二次会议和八届五中全会被增选为中央政治局常委和中共中央","box":[[76,935],[815,935],[815,952],[76,952]]},{"text":"副主席。一年后彭德怀被打倒，林彪又取代彭主持中央军委工作。","box":[[76,969],[668,969],[668,989],[76,989]]},{"text":"毛泽东重用林彪的原因，除了在长期的战争年代形成的信任、器重和关爱之","box":[[122,1006],[814,1006],[814,1024],[122,1024]]},{"text":"外，更重要的是，他非常需要林彪协助他执掌军权。","box":[[76,1040],[545,1041],[545,1059],[76,1058]]},{"text":"了解毛泽东思想的人都知道，毛有一句名言：“枪杆子里面出政权”。毛泽东","box":[[122,1075],[816,1075],[816,1095],[122,1095]]},{"text":"曾评价蒋介右称：“有军则有权，战争解决一切，这个基点，他是抓的很紧的。","box":[[79,1112],[802,1112],[802,1129],[79,1129]]},{"text":"对于这点，我们应向他学习。”的确是这样，毛泽东一生也是视军队为命根子，最","box":[[76,1147],[816,1147],[816,1164],[76,1164]]},{"text":"重掌控军权的。他始终将主要的关注点放在枪杆子上，称：“我们的原则是党指","box":[[77,1182],[815,1182],[815,1199],[77,1199]]}],"dimensions":{"height":1346,"width":939}}