{"ocr_results":[{"text":"第八章1967-69·下：山岳潜形","box":[[496,58],[744,58],[744,75],[496,75]]},{"text":"797","box":[[816,57],[852,57],[852,77],[816,77]]},{"text":"评教育。这样，在二十一军军部和支左委员会联络组门前静坐的群众，被迫于","box":[[122,128],[772,129],[772,149],[122,148]]},{"text":"9月19日全部撤回，那时在军部门前静坐的只有80多人了。9月中旬，总理","box":[[122,164],[772,165],[772,185],[122,184]]},{"text":"要黄、胡到北京汇报情况，做东派头头的工作，15日下午，总理接见黄、胡，","box":[[123,200],[759,201],[759,221],[123,220]]},{"text":"听取了简要汇报，指示我们要认真学习、宣传、贯彻毛主席视察大江南北的重","box":[[125,236],[771,237],[771,255],[125,254]]},{"text":"要指示，抓紧做好两派的联合工作。根据毛主席关于“地方的问题在军队，","box":[[122,270],[760,272],[760,292],[122,290]]},{"text":"军队的问题在工作”的指示，中央、总理要西安四家部队的主要领导同志和负","box":[[124,308],[771,308],[771,325],[124,325]]},{"text":"责支左工作的领导同志到北京开会，粟裕、杨成武、洗恒汉同志还有邱会作","box":[[123,342],[771,343],[771,361],[123,360]]},{"text":"代表中央领导主持会议，经过分析形势，总结支左开始以来的工作，大家一","box":[[122,376],[773,378],[773,398],[122,396]]},{"text":"致认为，支左委员会对支左工作的领导和对一些较大问题的处理是正确的，","box":[[124,413],[757,415],[757,432],[124,430]]},{"text":"一些原来或明或暗支持一派的同志也都作了自我批评。1月2日晚，政治局接","box":[[122,447],[773,449],[773,469],[122,467]]},{"text":"见了到会的同志，对会议的情况表示满意，对省支左委员会的工作作了肯定，","box":[[123,483],[760,485],[760,505],[123,503]]},{"text":"指示我们要认真贯彻毛主席视察大江南北的指示，促进大联合，发展全省形","box":[[123,519],[771,521],[771,539],[123,537]]},{"text":"势，并决定陕西不再成立革命委员会筹备小组，由支左委员会和群众协商，提","box":[[121,554],[773,556],[773,576],[121,574]]},{"text":"出成立省革命委员会的方案。同时确定调省军区系统的大部分干部到京办学习","box":[[124,589],[769,591],[769,611],[124,609]]},{"text":"班，学习提高。总理和中央领导同志的指示，使到会同志受到很大的教育和","box":[[121,625],[772,626],[772,646],[121,645]]},{"text":"鼓舞。【1663】","box":[[119,661],[217,650],[219,675],[122,686]]},{"text":"三、省革委会成立前后","box":[[340,722],[555,722],[555,742],[340,742]]},{"text":"很快到了1968年。关于省革委会成立前后的情况，胡炜晚年回忆称：","box":[[121,765],[751,766],[751,786],[121,785]]},{"text":"在大联合形成的高潮中，宝鸡地区、宝鸡市、虢镇、临潼等县和一批基","box":[[163,812],[772,813],[772,833],[163,832]]},{"text":"层单位陆续建立了三结合的革命委员会。省支左委员会认为，应当抓紧有利时","box":[[121,847],[771,848],[771,868],[121,867]]},{"text":"机，尽快地把陕西省和西安市革命委员会建立起来。1968年2、3月间，支","box":[[121,883],[772,884],[772,904],[121,903]]},{"text":"左委员会召集两大派头头60余人开会，协商成立省和西安市革委会的方案。","box":[[121,918],[758,919],[758,939],[121,938]]},{"text":"根据中央关于成立省革委会的原则指示，参照已建立省革委会的人员组成情","box":[[121,953],[770,954],[770,974],[121,973]]},{"text":"况，对省和西安市革委会的组成人员统筹安排，经过反复协商、研究，确定","box":[[121,988],[771,989],[771,1009],[121,1008]]},{"text":"省革委会由149名委员组成，设常委35名，正、副主任八名（主任由中央确","box":[[121,1022],[771,1024],[771,1044],[121,1042]]},{"text":"定），关于参加省革委会的群众代表，除宝鸡地区已选定外，其它地区革委会","box":[[122,1059],[770,1060],[770,1078],[122,1077]]},{"text":"尚未建立，参加省革委会的群众代表只确定了10名工、农劳动模范，其余暂","box":[[123,1095],[770,1095],[770,1112],[123,1112]]},{"text":"空缺，待各地区成立革委会后补选。协商中争执的焦点是省委第一书记霍士","box":[[122,1129],[769,1130],[769,1148],[122,1147]]},{"text":"廉同志，西派提出霍必须参加结合，东派坚决反对，霍是否参加结合牵涉到","box":[[122,1163],[771,1164],[771,1184],[122,1183]]},{"text":"【1663】《征程纪事》续集，页27-33。","box":[[73,1240],[371,1241],[371,1261],[73,1260]]}],"dimensions":{"height":1344,"width":938}}