{"ocr_results":[{"text":"966","box":[[85,42],[119,42],[119,61],[85,61]]},{"text":"风暴历程一文革中的人民解放军","box":[[171,36],[463,35],[463,55],[172,56]]},{"text":"枉，现在平反完全应该。问题在哪里？问题在于冤枉刘少奇的问题上责任不能","box":[[160,110],[810,108],[810,128],[160,130]]},{"text":"乱推，不负责任地推给林彪、江青，使别人对我们党的公信程度有质疑。","box":[[161,146],[765,144],[766,164],[161,166]]},{"text":"（二）批判“二月逆流”。在八届十二中全会上批判“二月逆流”是重点。","box":[[203,182],[799,180],[799,199],[203,201]]},{"text":"这真是此一时彼一时，其实在批判“二月逆流”的时候，大家发言都很积极","box":[[164,218],[794,218],[794,235],[164,235]]},{"text":"被批判的人也是什么都承认，自己骂自己，骂得狗血喷头，尤其几个元帅，他","box":[[162,252],[811,251],[811,271],[162,272]]},{"text":"们批判自已甚至比批判他们的人调子还高。","box":[[162,287],[506,288],[506,308],[162,307]]},{"text":"总理在会上批判“二月逆流”也是重头戏，他挨个批判了这些老同志","box":[[205,324],[795,324],[795,341],[205,341]]},{"text":"尤其是几个元帅，总理批得很厉害，也很具体。在我的记忆里，总理对聂","box":[[164,360],[811,360],[811,377],[164,377]]},{"text":"帅特别不满意，说他把国防科委系统搞得乱七八糟，甚至说他把赵尔陆给逼","box":[[164,396],[811,396],[811,413],[164,413]]},{"text":"死了。对于总理的讲话，我当时就有些不同的看法，因为我认为在坚持部队","box":[[163,430],[809,430],[809,450],[163,450]]},{"text":"不能乱，在保护军队老干部方面，叶帅、聂帅和徐帅的态度和做法是有区别","box":[[163,466],[810,466],[810,486],[163,486]]},{"text":"的。【1955】","box":[[160,501],[235,490],[238,512],[163,523]]},{"text":"列席全会的中央组织部业务组负责人郭玉峰回忆称：","box":[[162,548],[631,549],[631,569],[162,568]]},{"text":"一九六八年某月某日接到中办通知，叫我参加党的八届十二中全会（扩","box":[[202,594],[811,596],[811,616],[202,614]]},{"text":"大）。某月某日开会，我坐在后排，与郭沫若同志在一排坐。我对郭老久闻大","box":[[162,630],[811,631],[811,651],[162,650]]},{"text":"名，但未见其人。这次相见也无多少话可说。会议开始了。陈伯达说文化大","box":[[161,665],[811,668],[811,688],[161,685]]},{"text":"革命取得很大成绩，应归功于江青同志。而江青则说功绩应归于陈。二人相","box":[[162,701],[811,702],[811,722],[162,721]]},{"text":"互吹棒一番。到写会议文件很多人就把文革功绩归功文革小组。组长是陈伯","box":[[162,737],[810,738],[810,758],[162,757]]},{"text":"达，副组长是江青。会上毛主席问苏振华同志情况。前边不知什么人讲了他一","box":[[161,772],[812,773],[812,793],[161,792]]},{"text":"些坏话。会上印了刘少奇的罪行材料。通过了开除刘的党籍决定。有人提开除","box":[[162,808],[811,809],[811,829],[162,828]]},{"text":"邓小平党籍。毛主席说：开除党籍很容易。一举手就行了。可是邓小平有两","box":[[162,843],[810,845],[810,865],[162,863]]},{"text":"大功劳，一他会反修，指他带代表团到莫斯科谈判说小个子打败了大个子苏","box":[[162,878],[812,880],[812,900],[162,898]]},{"text":"斯洛夫。二是他会打仗。还是不开除党籍好。主席又很风趣的问汪东兴把邓","box":[[161,914],[811,915],[811,935],[161,934]]},{"text":"给办公厅工作怎么样？汪东兴当即回答不要、不要。他还说邓很小气。下放","box":[[161,950],[811,952],[811,971],[161,969]]},{"text":"时他把窗帘都拿走了....等。这时张云逸同志发言批判邓小平在右江红七军工","box":[[163,984],[811,987],[811,1006],[163,1003]]},{"text":"作时逃跑。说当时白色恐怖很厉害，他不辞而别了。毛主席听不清他的发言。","box":[[161,1019],[799,1021],[799,1042],[161,1040]]},{"text":"周恩来同志叫张云逸同志到主席跟前去讲。他讲了后，毛主席又问陈毅同志来","box":[[161,1055],[811,1056],[811,1076],[161,1075]]},{"text":"了没有？陈说来了，我反过主席。毛主席说你反过几次。陈答我反过六次。","box":[[163,1090],[798,1091],[798,1111],[163,1110]]},{"text":"毛主席说反我多少次我也团结你。毛主席问郭沫若，郭老，你是尊孔的，我","box":[[161,1125],[811,1126],[811,1146],[161,1145]]},{"text":"赞成范老范文澜同志，他是反孔的。在这次会议后我编在黄永胜、姚文元，","box":[[161,1159],[797,1162],[797,1182],[161,1179]]},{"text":"【1955】《邱会作回忆录》下，页601-602。","box":[[114,1222],[445,1225],[445,1244],[114,1241]]}],"dimensions":{"height":1344,"width":936}}