{"ocr_results":[{"text":"第十章1969-70：越风骤雨","box":[[519,56],[743,56],[743,73],[519,73]]},{"text":"1051","box":[[805,56],[848,56],[848,74],[805,74]]},{"text":"20.对外经济联络部","box":[[122,127],[297,127],[297,147],[122,147]]},{"text":"核心小组组长方毅，副组长刘大煜。革命委员会由20人组成，军队代表3","box":[[121,162],[819,163],[819,184],[121,183]]},{"text":"名，占15%。主任方毅，副主任刘大煜、钟羽一、谢怀德、张文敏。【2086核心小","box":[[76,194],[818,194],[818,221],[76,221]]},{"text":"组副组长1人为现役军人。革委会副主任4人中2人为现役军人，占50%。","box":[[77,235],[744,235],[744,255],[77,255]]},{"text":"21.公安部","box":[[122,271],[212,271],[212,289],[122,289]]},{"text":"核心小组组长李震，副组长于桑、曾威。革命委员会由27人组成，军队代表","box":[[121,304],[818,305],[818,326],[121,325]]},{"text":"10名，占37%。主任李震，副主任于桑、曾威、施义之、赵登程。2087]核心小组","box":[[75,334],[819,334],[819,364],[75,364]]},{"text":"组长、革委会主任李震为现役军人。核心小组副组长2人中1人为现役军人，占","box":[[79,378],[816,378],[816,395],[79,395]]},{"text":"50%。革委会副主任4人中3人为现役军人，占75%。","box":[[77,411],[548,412],[548,432],[77,431]]},{"text":"22.国务院办公室","box":[[121,447],[276,447],[276,467],[121,467]]},{"text":"核心小组组长丁江，副组长吴庆彤。[2088]国务院办公室不设革命委员会。核","box":[[118,474],[822,474],[822,507],[118,507]]},{"text":"心小组组长丁江为现役军人。","box":[[78,519],[330,519],[330,539],[78,539]]},{"text":"23.中国科学院","box":[[121,554],[254,554],[254,574],[121,574]]},{"text":"革命委员会由45人组成，军队代表10名，占22%。主任郭沫若，副主任李","box":[[123,591],[816,591],[816,608],[123,608]]},{"text":"四光、刘西尧、石煌、崔星。成立后仍保留院长、副院长名义。[2089]革委会副主","box":[[75,616],[821,616],[821,649],[75,649]]},{"text":"任4人中2人为现役军人，占50%。","box":[[78,661],[391,661],[391,682],[78,682]]},{"text":"以上中央6月22日批准的国务院22个部门党的核心小组组长中，17位为现","box":[[124,699],[816,699],[816,716],[124,716]]},{"text":"役军人。另五机部邱创成稍后于1970年12月恢复军职，被任命为总后副部长后，","box":[[77,732],[803,733],[803,753],[77,752]]},{"text":"即增至18位，占总数的82%。18人中，文革前的中将2人，少将11人，大校级","box":[[79,770],[816,770],[816,787],[79,787]]},{"text":"别5人。在21位革委会主任中，连邱创成为15位现役军人，占总数的71%。其中","box":[[78,804],[817,804],[817,824],[78,824]]},{"text":"文革前中将2人，少将10人，大校级别3人。可以说，此一时期的国务院各部门，","box":[[79,841],[802,841],[802,858],[79,858]]},{"text":"基本上是少将及大校们的天下。这集中反映了军队介入地方文革、三支两军后的","box":[[79,876],[816,876],[816,893],[79,893]]},{"text":"既成事实。","box":[[78,911],[169,911],[169,929],[78,929]]},{"text":"【2086】方毅，原对外经委主任。刘大煜，时任对外经委军管小组组长。钟羽一，时任对外经","box":[[74,1036],[818,1035],[818,1055],[74,1056]]},{"text":"委军管小组副组长。谢怀德，原对外经委副主任。张文敏，对外经委办公厅打字员。","box":[[141,1059],[795,1058],[795,1078],[142,1079]]},{"text":"【2087】李震，公安部领导小组成员，沈阳军区副政委。1955年授衔少将。于桑，公安部领","box":[[76,1082],[817,1082],[817,1099],[76,1099]]},{"text":"导小组成员，原公安部副部长。曾威，公安部领导小组成员，北京军区工程兵政委。","box":[[143,1105],[808,1104],[808,1122],[143,1123]]},{"text":"1955年授衔少将。施义之，公安部领导小组成员，陆军第二十一军政委。1955年授衔","box":[[141,1128],[817,1127],[817,1145],[142,1146]]},{"text":"大校。赵登程，公安部领导小组成员，空军第八军副军长。1965年空军大校军衔。","box":[[144,1151],[783,1151],[783,1168],[144,1168]]},{"text":"【2088】丁江，时任国务院直属口军代表。吴庆彤，国务院秘书厅秘书室主任。","box":[[77,1174],[689,1174],[689,1191],[77,1191]]},{"text":"【2089】郭沫若，原中国科学院院长。李四光，原地质部部长，1970年8月任国务院科教组","box":[[74,1195],[818,1194],[818,1214],[74,1215]]},{"text":"组长。刘西尧，原二机部副部长，国务院总理联络员。石煌，时任国家科委军管会主","box":[[140,1218],[818,1217],[818,1237],[141,1238]]},{"text":"任。崔星，时任国家科委军管会副主任。","box":[[143,1241],[454,1242],[454,1260],[142,1259]]}],"dimensions":{"height":1345,"width":938}}